stateutil/__init__.py
stateutil/_metadata.py
stateutil/incrementer.py
stateutil/persist.py
stateutil/switch.py
stateutil/unittests/__init__.py
stateutil/unittests/test_incrementor.py
stateutil/unittests/test_switch.py
stateutil-1.4.0.dist-info/LICENSE.txt
stateutil-1.4.0.dist-info/METADATA
stateutil-1.4.0.dist-info/RECORD
stateutil-1.4.0.dist-info/WHEEL
stateutil-1.4.0.dist-info/entry_points.txt
stateutil-1.4.0.dist-info/top_level.txt
