Metadata-Version: 2.1
Name: stateutil
Version: 1.4.0
Summary: A collection of state machine utilities.
Home-page: https://bitbucket.org/daycoder/stateutil.git
Author: Hywel Thomas
Author-email: hywel.thomas@mac.com
License: MIT
Download-URL: https://bitbucket.org/daycoder/stateutil.git/get/1.4.0.tar
Platform: UNKNOWN
Classifier: Development Status :: 3 - Alpha
Classifier: Intended Audience :: Developers
Classifier: License :: OSI Approved :: MIT License
Classifier: Programming Language :: Python :: 2
Classifier: Programming Language :: Python :: 2.7
Classifier: Programming Language :: Python :: 3
Classifier: Programming Language :: Python :: 3.6
Classifier: Topic :: Utilities
Requires-Dist: pip (>=9.0.1)
Requires-Dist: classutils (>=1.16.0)
Requires-Dist: fdutil (>=1.7.8)
